{"summaries":[{"symbol":{"__symbol":0,"members":[]},"metadata":{"__symbolic":"class","members":{"__ctor__":[{"__symbolic":"constructor","parameters":[{"__symbol":1,"members":[]},{"__symbol":2,"members":[]}]}],"passwordFeedback":[{"__symbolic":"method"}],"extractValues":[{"__symbolic":"method"}]}}}],"symbols":[{"__symbol":0,"name":"SignUpAndUpdatePassword","filePath":"C:/Users/antho/Advanced Cyber Security/Assignment two/Assignment/assets/app/login/SignandUpdatePassword.d.ts"},{"__symbol":1,"name":"UserService","filePath":"C:/Users/antho/Advanced Cyber Security/Assignment two/Assignment/assets/app/login/login.service.d.ts"},{"__symbol":2,"name":"Router","filePath":"C:/Users/antho/Advanced Cyber Security/Assignment two/Assignment/node_modules/@angular/router/router.d.ts"}]}